<?xml version="1.0" encoding="UTF-8"?>
<!--Sample XML file generated by XMLSpy v2010 rel. 3 sp1 (http://www.altova.com)-->
<!DOCTYPE LIMES SYSTEM "limes.dtd">
<LIMES>
	<PREFIX>
		<NAMESPACE>http://www.w3.org/1999/02/22-rdf-syntax-ns#</NAMESPACE>
		<LABEL>rdf</LABEL>
	</PREFIX>
	<PREFIX>
		<NAMESPACE>http://www.w3.org/2000/01/rdf-schema#</NAMESPACE>
		<LABEL>rdfs</LABEL>
	</PREFIX>
	<PREFIX>
		<NAMESPACE>http://www.w3.org/2002/07/owl/#</NAMESPACE>
		<LABEL>owl</LABEL>
	</PREFIX>
	<PREFIX>
		<NAMESPACE>http://oaei.ontologymatching.org/2010/IIMBTBOX/</NAMESPACE>
		<LABEL>imbt</LABEL>
	</PREFIX>

	<SOURCE>
		<ID>ontBig1</ID>
		<ENDPOINT>C:\Users\couco\Downloads\LIMES.0.6.RC4-2\LIMES.0.6.RC4-2\Release_Examples\ontBig.nt</ENDPOINT>
		<VAR>?x</VAR>
		<PAGESIZE>5000</PAGESIZE>
		<RESTRICTION></RESTRICTION>
		<PROPERTY>imbt:name</PROPERTY>
		<TYPE>N-TRIPLES</TYPE>
	</SOURCE>
	<TARGET>
		<ID>output</ID>
		<ENDPOINT>C:\Users\couco\Downloads\LIMES.0.6.RC4-2\LIMES.0.6.RC4-2\Release_Examples\output_file.nt</ENDPOINT>
		<VAR>?y</VAR>
		<PAGESIZE>5000</PAGESIZE>
		<RESTRICTION></RESTRICTION>
		<PROPERTY>imbt:name</PROPERTY>
		<TYPE>N-TRIPLES</TYPE>
	</TARGET>
	<METRIC>jaro(x.imbt:name,y.imbt:name)</METRIC>
	<ACCEPTANCE>
		<THRESHOLD>0.9</THRESHOLD>
		<FILE>Projet_v1_big.nt</FILE>
		<RELATION>owl:sameAs</RELATION>
	</ACCEPTANCE>
	<REVIEW>
		<THRESHOLD>0.7</THRESHOLD>
		<FILE>Projet_v2_review_big.nt</FILE>
		<RELATION>owl:sameAs</RELATION>
	</REVIEW>
	<EXECUTION>Simple</EXECUTION>
	<OUTPUT>TTL</OUTPUT>
</LIMES>